ros_rosidl_typesupport_fastrtps_c-3.8.1.data/data/include/rosidl_typesupport_fastrtps_c/rosidl_typesupport_fastrtps_c/identifier.h
ros_rosidl_typesupport_fastrtps_c-3.8.1.data/data/include/rosidl_typesupport_fastrtps_c/rosidl_typesupport_fastrtps_c/serialization_helpers.hpp
ros_rosidl_typesupport_fastrtps_c-3.8.1.data/data/include/rosidl_typesupport_fastrtps_c/rosidl_typesupport_fastrtps_c/visibility_control.h
ros_rosidl_typesupport_fastrtps_c-3.8.1.data/data/include/rosidl_typesupport_fastrtps_c/rosidl_typesupport_fastrtps_c/wstring_conversion.hpp
ros_rosidl_typesupport_fastrtps_c-3.8.1.data/data/lib/librosidl_typesupport_fastrtps_c.so
ros_rosidl_typesupport_fastrtps_c-3.8.1.data/data/lib/python3.14/site-packages/rosidl_typesupport_fastrtps_c/__init__.py
ros_rosidl_typesupport_fastrtps_c-3.8.1.data/data/lib/python3.14/site-packages/rosidl_typesupport_fastrtps_c/cli.py
ros_rosidl_typesupport_fastrtps_c-3.8.1.data/data/lib/python3.14/site-packages/rosidl_typesupport_fastrtps_c/__pycache__/__init__.cpython-314.pyc
ros_rosidl_typesupport_fastrtps_c-3.8.1.data/data/lib/python3.14/site-packages/rosidl_typesupport_fastrtps_c/__pycache__/cli.cpython-314.pyc
ros_rosidl_typesupport_fastrtps_c-3.8.1.data/data/lib/python3.14/site-packages/rosidl_typesupport_fastrtps_c-3.8.1-py3.14.egg-info/PKG-INFO
ros_rosidl_typesupport_fastrtps_c-3.8.1.data/data/lib/python3.14/site-packages/rosidl_typesupport_fastrtps_c-3.8.1-py3.14.egg-info/SOURCES.txt
ros_rosidl_typesupport_fastrtps_c-3.8.1.data/data/lib/python3.14/site-packages/rosidl_typesupport_fastrtps_c-3.8.1-py3.14.egg-info/dependency_links.txt
ros_rosidl_typesupport_fastrtps_c-3.8.1.data/data/lib/python3.14/site-packages/rosidl_typesupport_fastrtps_c-3.8.1-py3.14.egg-info/entry_points.txt
ros_rosidl_typesupport_fastrtps_c-3.8.1.data/data/lib/python3.14/site-packages/rosidl_typesupport_fastrtps_c-3.8.1-py3.14.egg-info/top_level.txt
ros_rosidl_typesupport_fastrtps_c-3.8.1.data/data/lib/rosidl_typesupport_fastrtps_c/rosidl_typesupport_fastrtps_c
ros_rosidl_typesupport_fastrtps_c-3.8.1.data/data/share/ament_index/resource_index/package_run_dependencies/rosidl_typesupport_fastrtps_c
ros_rosidl_typesupport_fastrtps_c-3.8.1.data/data/share/ament_index/resource_index/packages/rosidl_typesupport_fastrtps_c
ros_rosidl_typesupport_fastrtps_c-3.8.1.data/data/share/ament_index/resource_index/parent_prefix_path/rosidl_typesupport_fastrtps_c
ros_rosidl_typesupport_fastrtps_c-3.8.1.data/data/share/ament_index/resource_index/rosidl_typesupport_c/rosidl_typesupport_fastrtps_c
ros_rosidl_typesupport_fastrtps_c-3.8.1.data/data/share/rosidl_typesupport_fastrtps_c/local_setup.bash
ros_rosidl_typesupport_fastrtps_c-3.8.1.dist-info/METADATA
ros_rosidl_typesupport_fastrtps_c-3.8.1.dist-info/WHEEL
ros_rosidl_typesupport_fastrtps_c-3.8.1.dist-info/entry_points.txt
ros_rosidl_typesupport_fastrtps_c-3.8.1.dist-info/top_level.txt
ros_rosidl_typesupport_fastrtps_c-3.8.1.dist-info/RECORD
