Metadata-Version: 2.4
Name: ros-rosidl-typesupport-fastrtps-c
Version: 3.8.1
Summary: A ROS package for generating C interfaces for rosidl typesupport using eProsima FastRTPS.
Requires-Dist: ros-ament-index-python~=1.11.0
Requires-Dist: ros-rosidl-pycommon~=4.9.5
Requires-Dist: ros-rosidl-runtime-c~=4.9.5
Requires-Dist: ros-fastcdr~=2.3.3
Requires-Dist: ros-rosidl-typesupport-interface~=4.9.5
Requires-Dist: ros-rmw~=7.8.2
Requires-Dist: ros-rosidl-cli~=4.9.5
Requires-Dist: ros-rosidl-typesupport-fastrtps-cpp~=3.8.1
Requires-Dist: ros-rosidl-runtime-cpp~=4.9.5
Dynamic: description
Dynamic: description-content-type
Dynamic: requires-dist
Dynamic: summary
